Workbook

Sheet 변수 정의서
A1: No | B1: 그룹 | C1: 분류 | D1: 대분류 | E1: 중분류 | F1: 인자 (어골도 출처) | G1: 구분 | H1: 변수명 | I1: 타입 | J1: 설명
A2: 1 | B2: 1. 내부 데이터 | C2: ① | D2: 영상 데이터 | E2: 영상 원본 | F2: DICOM 파일 | G2: 변수 | H2: img_file_path | I2: VARCHAR(255) | J2: 비식별 처리 후 DICOM 원본 저장 경로
A3: 2 | B3: 1. 내부 데이터 | C3: ① | D3: 영상 데이터 | E3: 영상 원본 | F3: 픽셀 해상도 | G3: 변수 | H3: img_resolution | I3: VARCHAR(20) | J3: 가로x세로 픽셀 (예 2048x2048)
A4: 3 | B4: 1. 내부 데이터 | C4: ① | D4: 영상 데이터 | E4: 영상 원본 | F4: Bit Depth | G4: 변수 | H4: img_bit_depth | I4: TINYINT | J4: 픽셀당 비트 수 (8 / 12 / 16)
A5: 4 | B5: 1. 내부 데이터 | C5: ① | D5: 영상 데이터 | E5: 영상 원본 | F5: 압축 방식 | G5: 변수 | H5: img_compress_cd | I5: CHAR(2) | J5: NO 무압축 / JL JPEG-LS / J2 JPEG2000
A6: 5 | B6: 1. 내부 데이터 | C6: ① | D6: 영상 데이터 | E6: 영상 원본 | F6: 시리즈 · 인스턴스 | G6: 변수 | H6: series_uid | I6: VARCHAR(64) | J6: DICOM Series Instance UID · 검사 1건에 N개
A7: 6 | B7: 1. 내부 데이터 | C7: ① | D7: 영상 데이터 | E7: 영상 원본 | F7: 파일 용량 | G7: 변수 | H7: img_bytes | I7: BIGINT | J7: 파일 크기(byte) · 저장 비용 산정용
A8: 7 | B8: 1. 내부 데이터 | C8: ① | D8: 영상 데이터 | E8: 촬영 조건 | F8: 촬영 부위 | G8: 변수 | H8: img_body_part | I8: VARCHAR(20) | J8: THORAX / ABDOMEN / LIMB 등 표준 부위 코드
A9: 8 | B9: 1. 내부 데이터 | C9: ① | D9: 영상 데이터 | E9: 촬영 조건 | F9: 자세(VD · DV · Lat) | G9: 변수 | H9: img_view_cd | I9: CHAR(3) | J9: VD / DV / LAT — 판독 정확도에 직접 영향
A10: 9 | B10: 1. 내부 데이터 | C10: ① | D10: 영상 데이터 | E10: 촬영 조건 | F10: kVp · mAs | G10: 변수 | H10: kvp, mas | I10: DECIMAL(5,1) | J10: 관전압·관전류량 · 각각 별도 컬럼으로 분리 저장
A11: 10 | B11: 1. 내부 데이터 | C11: ① | D11: 영상 데이터 | E11: 촬영 조건 | F11: 촬영 거리(SID) | G11: 변수 | H11: sid_cm | I11: SMALLINT | J11: 초점-검출기 거리(cm) · 확대율 보정에 사용
A12: 11 | B12: 1. 내부 데이터 | C12: ① | D12: 영상 데이터 | E12: 촬영 조건 | F12: 그리드 사용 | G12: 변수 | H12: grid_yn | I12: CHAR(1) | J12: Y / N · 산란선 제거 격자 사용 여부
A13: 12 | B13: 1. 내부 데이터 | C13: ① | D13: 영상 데이터 | E13: 촬영 조건 | F13: 조영제 사용 | G13: 변수 | H13: contrast_yn | I13: CHAR(1) | J13: Y / N · 판독 해석 분기 조건
... A529: 528 | B529: 2. 외부 데이터 | C529: ⑪ | D529: 법제 · 규제 리스크 | E529: 기술 신뢰성 · XAI | F529: 오진 · 책임 소재 | G529: 준거 | H529: — | I529: — | J529: 오진 시 책임 소재 — 계약·면책 조항 설계 준거

Sheet 대분류별 집계
A1: 분류 | B1: 대분류 | C1: 그룹 | D1: 인자 수 | E1: 변수 | F1: 파생 | G1: 코드값 | H1: 참조 | I1: 준거
A2: ① | B2: 영상 데이터 | C2: 1. 내부 데이터 | D2: =COUNTIF('변수 정의서'!$D$2:$D$529,$B$2) -> 48 | E2: =COUNTIFS('변수 정의서'!$D$2:$D$529,$B$2,'변수 정의서'!$G$2:$G$529,"변수") -> 40 | F2: =COUNTIFS('변수 정의서'!$D$2:$D$529,$B$2,'변수 정의서'!$G$2:$G$529,"파생") -> 5 | G2: =COUNTIFS('변수 정의서'!$D$2:$D$529,$B$2,'변수 정의서'!$G$2:$G$529,"코드값") -> 0 | H2: =COUNTIFS('변수 정의서'!$D$2:$D$529,$B$2,'변수 정의서'!$G$2:$G$529,"참조") -> 0 | I2: =COUNTIFS('변수 정의서'!$D$2:$D$529,$B$2,'변수 정의서'!$G$2:$G$529,"준거") -> 3
A3: ② | B3: 혈액 · 진단검사 | C3: 1. 내부 데이터 | D3: =COUNTIF('변수 정의서'!$D$2:$D$529,$B$3) -> 48 | E3: =COUNTIFS('변수 정의서'!$D$2:$D$529,$B$3,'변수 정의서'!$G$2:$G$529,"변수") -> 11 | F3: =COUNTIFS('변수 정의서'!$D$2:$D$529,$B$3,'변수 정의서'!$G$2:$G$529,"파생") -> 4 | G3: =COUNTIFS('변수 정의서'!$D$2:$D$529,$B$3,'변수 정의서'!$G$2:$G$529,"코드값") -> 25 | H3: =COUNTIFS('변수 정의서'!$D$2:$D$529,$B$3,'변수 정의서'!$G$2:$G$529,"참조") -> 4 | I3: =COUNTIFS('변수 정의서'!$D$2:$D$529,$B$3,'변수 정의서'!$G$2:$G$529,"준거") -> 4
A4: ③ | B4: 처방 · 투약 | C4: 1. 내부 데이터 | D4: =COUNTIF('변수 정의서'!$D$2:$D$529,$B$4) -> 48 | E4: =COUNTIFS('변수 정의서'!$D$2:$D$529,$B$4,'변수 정의서'!$G$2:$G$529,"변수") -> 33 | F4: =COUNTIFS('변수 정의서'!$D$2:$D$529,$B$4,'변수 정의서'!$G$2:$G$529,"파생") -> 13 | G4: =COUNTIFS('변수 정의서'!$D$2:$D$529,$B$4,'변수 정의서'!$G$2:$G$529,"코드값") -> 0 | H4: =COUNTIFS('변수 정의서'!$D$2:$D$529,$B$4,'변수 정의서'!$G$2:$G$529,"참조") -> 1 | I4: =COUNTIFS('변수 정의서'!$D$2:$D$529,$B$4,'변수 정의서'!$G$2:$G$529,"준거") -> 1
A5: ④ | B5: 응급 · 입원 | C5: 1. 내부 데이터 | D5: =COUNTIF('변수 정의서'!$D$2:$D$529,$B$5) -> 48 | E5: =COUNTIFS('변수 정의서'!$D$2:$D$529,$B$5,'변수 정의서'!$G$2:$G$529,"변수") -> 40 | F5: =COUNTIFS('변수 정의서'!$D$2:$D$529,$B$5,'변수 정의서'!$G$2:$G$529,"파생") -> 7 | G5: =COUNTIFS('변수 정의서'!$D$2:$D$529,$B$5,'변수 정의서'!$G$2:$G$529,"코드값") -> 0 | H5: =COUNTIFS('변수 정의서'!$D$2:$D$529,$B$5,'변수 정의서'!$G$2:$G$529,"참조") -> 0 | I5: =COUNTIFS('변수 정의서'!$D$2:$D$529,$B$5,'변수 정의서'!$G$2:$G$529,"준거") -> 1
A6: ⑤ | B6: 개체 · 보호자 마스터 | C6: 1. 내부 데이터 | D6: =COUNTIF('변수 정의서'!$D$2:$D$529,$B$6) -> 48 | E6: =COUNTIFS('변수 정의서'!$D$2:$D$529,$B$6,'변수 정의서'!$G$2:$G$529,"변수") -> 42 | F6: =COUNTIFS('변수 정의서'!$D$2:$D$529,$B$6,'변수 정의서'!$G$2:$G$529,"파생") -> 3 | G6: =COUNTIFS('변수 정의서'!$D$2:$D$529,$B$6,'변수 정의서'!$G$2:$G$529,"코드값") -> 0 | H6: =COUNTIFS('변수 정의서'!$D$2:$D$529,$B$6,'변수 정의서'!$G$2:$G$529,"참조") -> 1 | I6: =COUNTIFS('변수 정의서'!$D$2:$D$529,$B$6,'변수 정의서'!$G$2:$G$529,"준거") -> 2
A7: ⑥ | B7: 통합 · 품질 · 거버넌스 | C7: 1. 내부 데이터 | D7: =COUNTIF('변수 정의서'!$D$2:$D$529,$B$7) -> 48 | E7: =COUNTIFS('변수 정의서'!$D$2:$D$529,$B$7,'변수 정의서'!$G$2:$G$529,"변수") -> 18 | F7: =COUNTIFS('변수 정의서'!$D$2:$D$529,$B$7,'변수 정의서'!$G$2:$G$529,"파생") -> 12 | G7: =COUNTIFS('변수 정의서'!$D$2:$D$529,$B$7,'변수 정의서'!$G$2:$G$529,"코드값") -> 0 | H7: =COUNTIFS('변수 정의서'!$D$2:$D$529,$B$7,'변수 정의서'!$G$2:$G$529,"참조") -> 5 | I7: =COUNTIFS('변수 정의서'!$D$2:$D$529,$B$7,'변수 정의서'!$G$2:$G$529,"준거") -> 13
A8: ⑦ | B8: 멀티모달 AI 학습 · 판독 | C8: 1. 내부 데이터 | D8: =COUNTIF('변수 정의서'!$D$2:$D$529,$B$8) -> 48 | E8: =COUNTIFS('변수 정의서'!$D$2:$D$529,$B$8,'변수 정의서'!$G$2:$G$529,"변수") -> 20 | F8: =COUNTIFS('변수 정의서'!$D$2:$D$529,$B$8,'변수 정의서'!$G$2:$G$529,"파생") -> 17 | G8: =COUNTIFS('변수 정의서'!$D$2:$D$529,$B$8,'변수 정의서'!$G$2:$G$529,"코드값") -> 0 | H8: =COUNTIFS('변수 정의서'!$D$2:$D$529,$B$8,'변수 정의서'!$G$2:$G$529,"참조") -> 3 | I8: =COUNTIFS('변수 정의서'!$D$2:$D$529,$B$8,'변수 정의서'!$G$2:$G$529,"준거") -> 8
A9: ⑧ | B9: 수의사용 판독 초안 | C9: 1. 내부 데이터 | D9: =COUNTIF('변수 정의서'!$D$2:$D$529,$B$9) -> 48 | E9: =COUNTIFS('변수 정의서'!$D$2:$D$529,$B$9,'변수 정의서'!$G$2:$G$529,"변수") -> 35 | F9: =COUNTIFS('변수 정의서'!$D$2:$D$529,$B$9,'변수 정의서'!$G$2:$G$529,"파생") -> 7 | G9: =COUNTIFS('변수 정의서'!$D$2:$D$529,$B$9,'변수 정의서'!$G$2:$G$529,"코드값") -> 0 | H9: =COUNTIFS('변수 정의서'!$D$2:$D$529,$B$9,'변수 정의서'!$G$2:$G$529,"참조") -> 0 | I9: =COUNTIFS('변수 정의서'!$D$2:$D$529,$B$9,'변수 정의서'!$G$2:$G$529,"준거") -> 6
A10: ⑨ | B10: 보호자 설명문 · 수익화 | C10: 1. 내부 데이터 | D10: =COUNTIF('변수 정의서'!$D$2:$D$529,$B$10) -> 48 | E10: =COUNTIFS('변수 정의서'!$D$2:$D$529,$B$10,'변수 정의서'!$G$2:$G$529,"변수") -> 29 | F10: =COUNTIFS('변수 정의서'!$D$2:$D$529,$B$10,'변수 정의서'!$G$2:$G$529,"파생") -> 17 | G10: =COUNTIFS('변수 정의서'!$D$2:$D$529,$B$10,'변수 정의서'!$G$2:$G$529,"코드값") -> 0 | H10: =COUNTIFS('변수 정의서'!$D$2:$D$529,$B$10,'변수 정의서'!$G$2:$G$529,"참조") -> 1 | I10: =COUNTIFS('변수 정의서'!$D$2:$D$529,$B$10,'변수 정의서'!$G$2:$G$529,"준거") -> 1
A11: ⑩ | B11: 보호자 신뢰 · 시장 대응 | C11: 2. 외부 데이터 | D11: =COUNTIF('변수 정의서'!$D$2:$D$529,$B$11) -> 48 | E11: =COUNTIFS('변수 정의서'!$D$2:$D$529,$B$11,'변수 정의서'!$G$2:$G$529,"변수") -> 3 | F11: =COUNTIFS('변수 정의서'!$D$2:$D$529,$B$11,'변수 정의서'!$G$2:$G$529,"파생") -> 13 | G11: =COUNTIFS('변수 정의서'!$D$2:$D$529,$B$11,'변수 정의서'!$G$2:$G$529,"코드값") -> 0 | H11: =COUNTIFS('변수 정의서'!$D$2:$D$529,$B$11,'변수 정의서'!$G$2:$G$529,"참조") -> 23 | I11: =COUNTIFS('변수 정의서'!$D$2:$D$529,$B$11,'변수 정의서'!$G$2:$G$529,"준거") -> 9
A12: ⑪ | B12: 법제 · 규제 리스크 | C12: 2. 외부 데이터 | D12: =COUNTIF('변수 정의서'!$D$2:$D$529,$B$12) -> 48 | E12: =COUNTIFS('변수 정의서'!$D$2:$D$529,$B$12,'변수 정의서'!$G$2:$G$529,"변수") -> 23 | F12: =COUNTIFS('변수 정의서'!$D$2:$D$529,$B$12,'변수 정의서'!$G$2:$G$529,"파생") -> 5 | G12: =COUNTIFS('변수 정의서'!$D$2:$D$529,$B$12,'변수 정의서'!$G$2:$G$529,"코드값") -> 0 | H12: =COUNTIFS('변수 정의서'!$D$2:$D$529,$B$12,'변수 정의서'!$G$2:$G$529,"참조") -> 10 | I12: =COUNTIFS('변수 정의서'!$D$2:$D$529,$B$12,'변수 정의서'!$G$2:$G$529,"준거") -> 10
B13: 합계 | D13: =SUM(D2:D12) -> 528 | E13: =SUM(E2:E12) -> 294 | F13: =SUM(F2:F12) -> 103 | G13: =SUM(G2:G12) -> 25 | H13: =SUM(H2:H12) -> 48 | I13: =SUM(I2:I12) -> 58

Sheet 고유 변수 목록
A1: No | B1: 변수명 | C1: 타입 | D1: 구분 | E1: 설명 | F1: 출처 인자 수 | G1: 최초 출처(대분류 · 중분류)
A2: 1 | B2: img_file_path | C2: VARCHAR(255) | D2: 변수 | E2: 비식별 처리 후 DICOM 원본 저장 경로 | F2: 1 | G2: ① 영상 원본
A3: 2 | B3: img_resolution | C3: VARCHAR(20) | D3: 변수 | E3: 가로x세로 픽셀 (예 2048x2048) | F3: 1 | G3: ① 영상 원본
A4: 3 | B4: img_bit_depth | C4: TINYINT | D4: 변수 | E4: 픽셀당 비트 수 (8 / 12 / 16) | F4: 1 | G4: ① 영상 원본
A5: 4 | B5: img_compress_cd | C5: CHAR(2) | D5: 변수 | E5: NO 무압축 / JL JPEG-LS / J2 JPEG2000 | F5: 1 | G5: ① 영상 원본
A6: 5 | B6: series_uid | C6: VARCHAR(64) | D6: 변수 | E6: DICOM Series Instance UID · 검사 1건에 N개 | F6: 1 | G6: ① 영상 원본
A7: 6 | B7: img_bytes | C7: BIGINT | D7: 변수 | E7: 파일 크기(byte) · 저장 비용 산정용 | F7: 1 | G7: ① 영상 원본
A8: 7 | B8: img_body_part | C8: VARCHAR(20) | D8: 변수 | E8: THORAX / ABDOMEN / LIMB 등 표준 부위 코드 | F8: 1 | G8: ① 촬영 조건
A9: 8 | B9: img_view_cd | C9: CHAR(3) | D9: 변수 | E9: VD / DV / LAT — 판독 정확도에 직접 영향 | F9: 1 | G9: ① 촬영 조건
A10: 9 | B10: kvp, mas | C10: DECIMAL(5,1) | D10: 변수 | E10: 관전압·관전류량 · 각각 별도 컬럼으로 분리 저장 | F10: 1 | G10: ① 촬영 조건
A11: 10 | B11: sid_cm | C11: SMALLINT | D11: 변수 | E11: 초점-검출기 거리(cm) · 확대율 보정에 사용 | F11: 1 | G11: ① 촬영 조건
A12: 11 | B12: grid_yn | C12: CHAR(1) | D12: 변수 | E12: Y / N · 산란선 제거 격자 사용 여부 | F12: 1 | G12: ① 촬영 조건
A13: 12 | B13: contrast_yn | C13: CHAR(1) | D13: 변수 | E13: Y / N · 판독 해석 분기 조건 | F13: 1 | G13: ① 촬영 조건
... A393: 392 | B393: vet_trust_score | C393: TINYINT | D393: 변수 | E393: 1~5 · 수의사 신뢰도 설문 | F393: 1 | G393: ⑪ 기술 신뢰성 · XAI

Sheet 표기 규칙
A1: 구분 | B1: 내용
A2: 작성 기준
B3: 본 정의서의 행은 [1. 데이터 수집성 평가표]의 인자 528개와 1:1로 대응한다. 인자 하나가 변수 하나가 되지 않는 경우도 있으므로 구분 열로 성격을 나눈다.
A5: 구분
A6: 변수 | B6: DB 컬럼으로 적재되는 값. 원천에서 직접 수집하거나 사용자가 입력한다.
A7: 파생 | B7: 다른 변수로부터 계산되는 값. 직접 입력 금지 — 산출 규칙이 정의되어야 한다.
A8: 코드값 | B8: 별도 컬럼이 아니라 기존 코드 컬럼(lab_item_cd 등)의 값으로 표현되는 항목. 검사 항목처럼 수가 많고 늘어나는 인자는 컬럼을 늘리지 않고 코드값으로 관리한다.
A9: 참조 | B9: 자사가 생성하지 않는 외부 기준값·통계·경쟁정보. 참조 테이블로 적재하며 출처와 조사 시점을 함께 기록한다.
A10: 준거 | B10: 컬럼이 아니라 설계 원칙·법령·운영 절차로 관리되는 항목. 변수명과 타입이 없다. 데이터로 저장되지 않지만 시스템이 지켜야 하므로 정의서에 남긴다.
A12: 명명 규칙
B13: snake_case 소문자. 식별자 _id · 코드 _cd · 일시 _dt · 여부 _yn · 비율 _rate · 금액 _amt · 경로 _path.
B14: 타입은 MySQL 8.0 기준. 코드성은 CHAR 고정길이, 명칭·경로는 VARCHAR, 서술형은 TEXT, 구조화 집합은 JSON.
A16: 그룹
A17: 1. 내부 데이터 | B17: 병원 진료 과정에서 발생하거나(①~⑤) 자사가 가공·생성하는(⑥~⑨) 데이터.
A18: 2. 외부 데이터 | B18: 시장·경쟁 조사값(⑩)과 법령·고시 준거(⑪). 자사가 생성하지 않으며 갱신 주기 관리 대상.
A20: 주의
B21: 동일 변수명이 여러 인자에 중복 등장할 수 있다(예 los_days). [고유 변수 목록] 시트에서 중복을 제거한 실제 컬럼 수를 확인할 것.
B22: 참조(R) 행의 수치는 공개 조사 통계이므로 인용 시 출처와 조사 연도를 반드시 병기한다.
